fds/__init__.py
fds/sdk/__init__.py
fds/sdk/Vault/__init__.py
fds/sdk/Vault/api_client.py
fds/sdk/Vault/configuration.py
fds/sdk/Vault/exceptions.py
fds/sdk/Vault/model_utils.py
fds/sdk/Vault/rest.py
fds/sdk/Vault/api/__init__.py
fds/sdk/Vault/api/accounts_api.py
fds/sdk/Vault/api/components_api.py
fds/sdk/Vault/api/configurations_api.py
fds/sdk/Vault/api/dates_api.py
fds/sdk/Vault/api/documents_api.py
fds/sdk/Vault/api/frequencies_api.py
fds/sdk/Vault/api/vault_calculations_api.py
fds/sdk/Vault/apis/__init__.py
fds/sdk/Vault/model/__init__.py
fds/sdk/Vault/model/account_directories.py
fds/sdk/Vault/model/account_directories_root.py
fds/sdk/Vault/model/calculation_meta.py
fds/sdk/Vault/model/calculation_status.py
fds/sdk/Vault/model/calculation_status_meta.py
fds/sdk/Vault/model/calculation_status_root.py
fds/sdk/Vault/model/calculation_unit_status.py
fds/sdk/Vault/model/calculation_unit_status_meta.py
fds/sdk/Vault/model/calculations_summary.py
fds/sdk/Vault/model/calculations_summary_root.py
fds/sdk/Vault/model/client_error_response.py
fds/sdk/Vault/model/component_summary.py
fds/sdk/Vault/model/component_summary_root.py
fds/sdk/Vault/model/configuration_account.py
fds/sdk/Vault/model/date_parameters_summary.py
fds/sdk/Vault/model/date_parameters_summary_root.py
fds/sdk/Vault/model/document_directories.py
fds/sdk/Vault/model/document_directories_root.py
fds/sdk/Vault/model/error.py
fds/sdk/Vault/model/error_source.py
fds/sdk/Vault/model/frequency.py
fds/sdk/Vault/model/frequency_root.py
fds/sdk/Vault/model/object_root.py
fds/sdk/Vault/model/pagination_info.py
fds/sdk/Vault/model/pagination_meta.py
fds/sdk/Vault/model/vault_calculation_parameters.py
fds/sdk/Vault/model/vault_calculation_parameters_root.py
fds/sdk/Vault/model/vault_component.py
fds/sdk/Vault/model/vault_component_root.py
fds/sdk/Vault/model/vault_configuration.py
fds/sdk/Vault/model/vault_configuration_root.py
fds/sdk/Vault/model/vault_configuration_summary.py
fds.sdk.Vault-2.0.2.dist-info/LICENSE
fds.sdk.Vault-2.0.2.dist-info/METADATA
fds.sdk.Vault-2.0.2.dist-info/WHEEL
fds.sdk.Vault-2.0.2.dist-info/top_level.txt
fds.sdk.Vault-2.0.2.dist-info/RECORD
